fms_acceleration_moe/__init__.py
fms_acceleration_moe/framework_plugin_scattermoe.py
fms_acceleration_moe/utils/__init__.py
fms_acceleration_moe/utils/checkpoint_utils.py
fms_acceleration_moe/utils/scattermoe.py
fms_acceleration_moe/utils/scattermoe_constants.py
fms_acceleration_moe/utils/scattermoe_prepare.py
fms_acceleration_moe/utils/scattermoe_state_dict.py
fms_acceleration_moe/utils/scattermoe_utils/__init__.py
fms_acceleration_moe/utils/scattermoe_utils/expert_parallel.py
fms_acceleration_moe/utils/scattermoe_utils/khd/__init__.py
fms_acceleration_moe/utils/scattermoe_utils/khd/custom_op.py
fms_acceleration_moe/utils/scattermoe_utils/khd/kernels/__init__.py
fms_acceleration_moe/utils/scattermoe_utils/khd/kernels/kernels.py
fms_acceleration_moe/utils/scattermoe_utils/khd/kernels/ops/__init__.py
fms_acceleration_moe/utils/scattermoe_utils/khd/kernels/ops/compileable_ops.py
fms_acceleration_moe/utils/scattermoe_utils/megablocks/__init__.py
fms_acceleration_moe/utils/scattermoe_utils/megablocks/autograd.py
fms_acceleration_moe/utils/scattermoe_utils/megablocks/kernels/__init__.py
fms_acceleration_moe/utils/scattermoe_utils/megablocks/kernels/gather_scatter.py
fms_acceleration_moe-0.4.6.dist-info/METADATA
fms_acceleration_moe-0.4.6.dist-info/WHEEL
fms_acceleration_moe-0.4.6.dist-info/RECORD
