Metadata-Version: 2.4
Name: fms-acceleration-moe
Version: 0.4.6
Summary: FMS Acceleration Plugin for Mixture-of-Experts
Author-email: Fabian Lim <flim@sg.ibm.com>
License: Apache-2.0
Keywords: acceleration,fms-hf-tuning,megablocks,mixture-of-experts,scattermoe
Classifier: Development Status :: 4 - Beta
Classifier: License :: OSI Approved :: Apache Software License
Classifier: Programming Language :: Python :: 3
Classifier: Programming Language :: Python :: 3.9
Classifier: Programming Language :: Python :: 3.10
Classifier: Programming Language :: Python :: 3.11
Requires-Python: ~=3.9
